orthopy/__init__.py
orthopy/_helpers.py
orthopy/c1/__init__.py
orthopy/c1/_tools.py
orthopy/c1/associated_legendre.py
orthopy/c1/chebyshev1.py
orthopy/c1/chebyshev2.py
orthopy/c1/gegenbauer.py
orthopy/c1/jacobi.py
orthopy/c1/legendre.py
orthopy/cn/__init__.py
orthopy/cn/_main.py
orthopy/cn/_tools.py
orthopy/e1r/__init__.py
orthopy/e1r/_main.py
orthopy/e1r/_tools.py
orthopy/e1r2/__init__.py
orthopy/e1r2/_main.py
orthopy/e1r2/_tools.py
orthopy/enr2/__init__.py
orthopy/enr2/_main.py
orthopy/enr2/_tools.py
orthopy/s2/__init__.py
orthopy/s2/_tools.py
orthopy/s2/xu.py
orthopy/s2/zernike.py
orthopy/s2/zernike2.py
orthopy/t2/__init__.py
orthopy/t2/_main.py
orthopy/t2/_tools.py
orthopy/tools/__init__.py
orthopy/tools/generate_rc.py
orthopy/u3/__init__.py
orthopy/u3/_main.py
orthopy-0.10.3.dist-info/METADATA
orthopy-0.10.3.dist-info/WHEEL
orthopy-0.10.3.dist-info/top_level.txt
orthopy-0.10.3.dist-info/RECORD
