Metadata-Version: 2.4
Name: orthopy
Version: 0.10.3
Summary: Orthogonal polynomials for Python
Author-email: Nico Schlömer <nico.schloemer@gmail.com>
License-Expression: LicenseRef-Proprietary
Project-URL: Homepage, https://github.com/sigma-py/orthopy
Project-URL: Issues, https://github.com/sigma-py/orthopy/issues
Classifier: Development Status :: 5 - Production/Stable
Classifier: Programming Language :: Python
Classifier: Programming Language :: Python :: 3
Classifier: Programming Language :: Python :: 3.9
Classifier: Programming Language :: Python :: 3.10
Classifier: Programming Language :: Python :: 3.11
Classifier: Programming Language :: Python :: 3.12
Classifier: Programming Language :: Python :: 3.13
Classifier: Topic :: Utilities
Classifier: Topic :: Scientific/Engineering
Classifier: Topic :: Scientific/Engineering :: Mathematics
Requires-Python: >=3.9
Requires-Dist: numpy
Requires-Dist: sympy
Requires-Dist: matplotlib
Requires-Dist: matplotx
Requires-Dist: stonefish-license-manager>=0.5.24
Provides-Extra: all
Requires-Dist: meshio; extra == "all"
Requires-Dist: meshzoo; extra == "all"
Requires-Dist: x22>=0.2.1
